_assembly/.flake8rc
_assembly/.pylintrc
_assembly/.style.yapf
_assembly/__init__.py
_assembly/__pycache__/__init__.cpython-39.pyc
_assembly/lib/util/log.py
_assembly/sdk/__init__.py
_assembly/sdk/_category_.json
_assembly/sdk/config/__init__.py
_assembly/sdk/config/options.py
_assembly/sdk/pytest_plugin/__init__.py
_assembly/sdk/pytest_plugin/arguments.py
_assembly/sdk/pytest_plugin/markers.py
_assembly/sdk/pytest_plugin/plugin.py
_assembly/sdk/pytest_plugin/fixtures/__init__.py
_assembly/sdk/pytest_plugin/fixtures/nodes_networks.py
_assembly/sdk/pytest_plugin/fixtures/pytest_args.py
_assembly/sdk/pytest_plugin/test/__init__.py
_assembly/sdk/pytest_plugin/test/conftest.py
_assembly/sdk/pytest_plugin/test/test_pytest_plugin.py
_assembly/sdk/pytest_plugin/test/contracts/data/contract.yaml
_assembly/sdk/pytest_plugin/test/contracts/data/data.sympl
_assembly/sdk/pytest_plugin/test/contracts/hello/1.0.0/contract.yaml
_assembly/sdk/pytest_plugin/test/contracts/hello/1.0.0/hello.sympl
_assembly/sdk/pytest_plugin/test/contracts/hello/1.0.1/contract.yaml
_assembly/sdk/pytest_plugin/test/contracts/hello/1.0.1/hello.sympl
_assembly/sdk/util/__init__.py
_assembly/sdk/util/junit.py
_assembly/sdk/util/readme.md
_assembly/sdk/util/timeout.py
test/__init__.py
test/test_pytest_plugin_integration_test.py
symbiont_io.pytest_assembly-4.1.0.dist-info/LICENSE
symbiont_io.pytest_assembly-4.1.0.dist-info/METADATA
symbiont_io.pytest_assembly-4.1.0.dist-info/WHEEL
symbiont_io.pytest_assembly-4.1.0.dist-info/entry_points.txt
symbiont_io.pytest_assembly-4.1.0.dist-info/top_level.txt
symbiont_io.pytest_assembly-4.1.0.dist-info/RECORD
