Metadata-Version: 2.1
Name: symbiont-io.pytest-assembly
Version: 4.1.0
Summary: Symbiont Assembly SDK
Home-page: http://symbiont.io
Author: Symbiont
Author-email: ecosystem@symbiont.io
Maintainer: Symbiont Ecosystem Team
Maintainer-email: ecosystem@symbiont.io
License: UNKNOWN
Keywords: symbiont,bitcoin
Platform: UNKNOWN
Classifier: Development Status :: 5 - Production/Stable
Classifier: Intended Audience :: Developers
Classifier: Intended Audience :: Financial and Insurance Industry
Classifier: Natural Language :: English
Classifier: Operating System :: POSIX
Classifier: Programming Language :: Python :: 3 :: Only 
Classifier: Topic :: Office/Business :: Financial
Classifier: Topic :: Software Development :: Libraries :: Python Modules
Classifier: Topic :: System :: Distributed Computing
Provides: sailfish
Requires-Dist: pytest-benchmark (==3.4.1)
Requires-Dist: pytest (==6.2.5)
Requires-Dist: symbiont-io.assembly-client (==4.1.0)
